<record xmlns="http://www.openarchives.org/OAI/2.0/" xmlns:xsi="http://www.w3.org/2001/XMLSchema-instance">
  <header>
    <identifier>oai:materialscloud.org:2019.0020/v1</identifier>
    <datestamp>2019-06-12Z</datestamp>
    <setSpec>DOI</setSpec>
  </header>
  <metadata>
    <oai_dc:dc xmlns:dc="http://purl.org/dc/elements/1.1/" xmlns:dcterms="http://purl.org/dc/dc/terms/" xmlns:oai_dc="http://www.openarchives.org/OAI/2.0/oai_dc/" xmlns:xsi="http://www.w3.org/2001/XMLSchema-instance" xsi:schemaLocation="http://www.openarchives.org/OAI/2.0/oai_dc/ http://www.openarchives.org/OAI/2.0/oai_dc.xsd">
      <dc:type>Dataset</dc:type>
      <dc:creator>Rhone, Trevor David</dc:creator>
      <dc:creator>Chen, Wei </dc:creator>
      <dc:creator>Desai, Shaan </dc:creator>
      <dc:creator>Yacoby, Amir</dc:creator>
      <dc:creator>Kaxiras, Efthimios</dc:creator>
      <dc:title>Data-driven studies of magnetic two-dimensional materials</dc:title>
      <dc:publisher>Materials Cloud</dc:publisher>
      <dc:date>2019-05-20</dc:date>
      <dc:rights>Creative Commons Attribution 4.0 International https://creativecommons.org/licenses/by/4.0/legalcode</dc:rights>
      <dc:rights>info:eu-repo/semantics/openAccess</dc:rights>
      <dc:subject>machine learning</dc:subject>
      <dc:subject>two-dimensional materials</dc:subject>
      <dc:subject>magnetic materials</dc:subject>
      <dc:identifier>doi:10.24435/materialscloud:2019.0020/v1</dc:identifier>
      <dc:identifier>https://archive.materialscloud.org/2019.0020/v1</dc:identifier>
      <dc:language>en</dc:language>
      <dc:description>We use a data-driven approach to study the magnetic and thermodynamic properties of van der Waals (vdW) layered materials. We investigate monolayers of the form A2B2X6, based on the known material Cr2Ge2Te6, using density functional theory (DFT) calculations and determine their magnetic properties, such as magnetic order and magnetic moment. We also examine formation energies and use them as a proxy for chemical stability. </dc:description>
    </oai_dc:dc>
  </metadata>
</record>
