<record xmlns="http://www.openarchives.org/OAI/2.0/" xmlns:xsi="http://www.w3.org/2001/XMLSchema-instance">
  <header>
    <identifier>oai:clarin-pl.eu:11321/298</identifier>
    <datestamp>2016-06-06T14:42:18Z</datestamp>
    <setSpec>hdl_11321_3</setSpec>
    <setSpec>hdl_11321_4</setSpec>
  </header>
  <metadata>
    <oai_dc:dc xmlns:oai_dc="http://www.openarchives.org/OAI/2.0/oai_dc/" xmlns:doc="http://www.lyncode.com/xoai" xmlns:xsi="http://www.w3.org/2001/XMLSchema-instance" xmlns:dc="http://purl.org/dc/elements/1.1/" xsi:schemaLocation="http://www.openarchives.org/OAI/2.0/oai_dc/ http://www.openarchives.org/OAI/2.0/oai_dc.xsd">
      <dc:title>NLP Web services and  NLP workflow engine</dc:title>
      <dc:creator>Walkowiak, Tomasz</dc:creator>
      <dc:subject>web services</dc:subject>
      <dc:subject>NLP tools</dc:subject>
      <dc:subject>language processing workflows</dc:subject>
      <dc:description>Web based system for natural language processing of texts in Polish. It allows running complex workflows of language and machine learning tools. Making it avaliable via REST Web Services.</dc:description>
      <dc:date>2016-04-01</dc:date>
      <dc:type>toolService</dc:type>
      <dc:identifier>http://hdl.handle.net/11321/298</dc:identifier>
      <dc:language>pol</dc:language>
      <dc:rights>GNU GPL3</dc:rights>
      <dc:rights>http://www.gnu.org/licenses/gpl-3.0.en.html</dc:rights>
      <dc:rights>PUB</dc:rights>
      <dc:format>text/plain; charset=utf-8</dc:format>
      <dc:format>application/zip</dc:format>
      <dc:format>downloadable_files_count: 1</dc:format>
      <dc:publisher>Wroclaw University of Science and Technology</dc:publisher>
      <dc:source>http://ws.clarin-pl.eu/</dc:source>
    </oai_dc:dc>
  </metadata>
</record>
