<record xmlns="http://www.openarchives.org/OAI/2.0/" xmlns:xsi="http://www.w3.org/2001/XMLSchema-instance">
  <header>
    <identifier>oai:lindat.mff.cuni.cz:11858/00-097C-0000-0001-4916-9</identifier>
    <datestamp>2018-07-02T22:05:53Z</datestamp>
    <setSpec>hdl_11858_00-097C-0000-0001-486F-D</setSpec>
    <setSpec>hdl_11858_00-097C-0000-0001-4877-A</setSpec>
  </header>
  <metadata>
    <oai_dc:dc xmlns:oai_dc="http://www.openarchives.org/OAI/2.0/oai_dc/" xmlns:doc="http://www.lyncode.com/xoai" xmlns:xsi="http://www.w3.org/2001/XMLSchema-instance" xmlns:dc="http://purl.org/dc/elements/1.1/" xsi:schemaLocation="http://www.openarchives.org/OAI/2.0/oai_dc/ http://www.openarchives.org/OAI/2.0/oai_dc.xsd">
      <dc:title>CzEng 0.7</dc:title>
      <dc:creator>Bojar, Ond&#345;ej</dc:creator>
      <dc:creator>&#381;abokrtsk&#253;, Zden&#283;k</dc:creator>
      <dc:creator>&#268;e&#353;ka, Pavel</dc:creator>
      <dc:creator>Be&#328;a, Peter</dc:creator>
      <dc:creator>Jan&#237;&#269;ek, Miroslav</dc:creator>
      <dc:subject>parallel corpus</dc:subject>
      <dc:description>CzEng 0.7 is a Czech-English parallel corpus compiled at the Institute of Formal and Applied Linguistics (&#218;FAL), Charles University, Prague. The corpus contains no manual annotation. It is limited only to texts which have been already available in an electronic form and which are not protected by authors' rights in the Czech Republic. The main purpose of the corpus is to support Czech-English and English-Czech machine translation research with the necessary data. CzEng 0.7 consists of a large set of parallel textual documents mainly from the fields of European law, information technology, and fiction, all of them converted into a uniform XML-based file format and provided with automatic sentence alignment.</dc:description>
      <dc:date>2009-11-02</dc:date>
      <dc:type>corpus</dc:type>
      <dc:identifier>http://hdl.handle.net/11858/00-097C-0000-0001-4916-9</dc:identifier>
      <dc:language>ces</dc:language>
      <dc:language>eng</dc:language>
      <dc:relation>http://hdl.handle.net/11234/1-1458</dc:relation>
      <dc:rights>Attribution-NonCommercial-ShareAlike 3.0 Unported (CC BY-NC-SA 3.0)</dc:rights>
      <dc:rights>http://creativecommons.org/licenses/by-nc-sa/3.0/</dc:rights>
      <dc:rights>PUB</dc:rights>
      <dc:format>application/zip</dc:format>
      <dc:format>text/plain; charset=utf-8</dc:format>
      <dc:format>downloadable_files_count: 1</dc:format>
      <dc:publisher>Charles University, Faculty of Mathematics and Physics, Institute of Formal and Applied Linguistics (UFAL)</dc:publisher>
      <dc:source>http://ufal.mff.cuni.cz/czeng/czeng07/</dc:source>
    </oai_dc:dc>
  </metadata>
</record>
