<record xmlns="http://www.openarchives.org/OAI/2.0/" xmlns:xsi="http://www.w3.org/2001/XMLSchema-instance">
  <header>
    <identifier>9dfd3aa056a411e2a2aa782bcb07413577c28fa1ac15497aaf1cb44bcd326db6</identifier>
    <datestamp>2018-11-15T16:40:00Z</datestamp>
    <setSpec>corpus</setSpec>
    <setSpec>corpus:text</setSpec>
  </header>
  <metadata>
    <oai_dc:dc xmlns:info="http://www.ilsp.gr/META-XMLSchema" xmlns:oai_dc="http://www.openarchives.org/OAI/2.0/oai_dc/" xmlns:dc="http://purl.org/dc/elements/1.1/" xsi:schemaLocation="http://www.openarchives.org/OAI/2.0/oai_dc/          http://www.openarchives.org/OAI/2.0/oai_dc.xsd">
      <dc:title>NPChunks</dc:title>
      <dc:description>The NPChunks training corpus contains approximately 1,000 sentences, in a total of 24,243 tokens, selected randomly from the written part of the CINTIL corpus (Barreto et al, 2006). The CINTIL corpus is a linguistically interpreted corpus of Portuguese composed of 1 Million annotated tokens from both written (689,124 tokens) and spoken (502,622 tokens) registers (http://cintil.ul.pt/pt/).</dc:description>
      <dc:date>2013-01-04</dc:date>
    </oai_dc:dc>
  </metadata>
</record>
