{
    "author": [
        "ICOS Atmospheric Thematic Centre @ LSCE, Paris, France"
    ],
    "Contact": [
        "Leonard Rivier;ICOS Atmospheric Thematic Centre @ LSCE, Paris, France"
    ],
    "Contributor": [
        "ICOS"
    ],
    "DOI": "",
    "DiscHierarchy": [
        "4.4.1",
        "Geosciences",
        "Atmospheric Sciences"
        "4.4.6"
        "Earth System Research"
    ],
    "Discipline": "Atmospheric Sciences","Environmental Research"
    "Format": [
        "text/csv; application/x-netcdf"
    ],
    "Language": [
        "English"
    ],
    "MetaDataAccess": "",
    "PublicationTimestamp": "2018-10-25T11:59:59Z",
    "PublicationYear": [
        "2017"
    ],
    "Publisher": [
        "ICOS Carbon Portal @ Lund University, Lund, Sweden"
    ],
    "RelatedIdentifier": [
        "http://doi.org/10.5281/zenodo.204817"
    ],
    "Contributor": [
        "ICOS"
    ],
    "ResourceType": [
        "Dataset series (INSPIRE); Collection (Dublin Core)"
    ],
    "Rights": [
        "Creative Commons 4.0 CC-BY"
    ],
    "SpatialCoverage": [
        "-20.0 35.0",
        "35.0 75.0"
    ],
    "TemporalCoverage:BeginDate": "2017-01-01T11:59:59Z",
    "TemporalCoverage:EndDate": "",

    "fulltext": "",
    "group": "envriplus",
    "groups": [
        {
            "name": "envriplus"
        }
    ],
    "name": "ffd2e5a7-7d16-53fd-a606-a3ef19d7357e",
    "notes": [
        "Near Real Time data, quality checked by automated processes. In general the data are daily available in 36 to 48 hours after actual measurement. The ICOS Atmospheric Station NRT data are mole fractions of (CO2, CH4) and other trace gases (e.g. CO). Concentration observations are done from towers with a footprint area of more than 100 km2. This data product is produced by the ICOS Atmospheric Thematic Centre (ICOS ATC; http://www.icos-atc.eu/)."
    ],
    "oai_identifier": [
        "b73648f1-2f43-52c8-b4e4-f071f16f4e61"
    ],
    "oai_set": "",
    "state": "active",
    "tags": [
        {
            "name": "Atmospheric"
        },
        {
            "name": "conditions"
        },
        {
            "name": "INSPIRE"
        },
        {
            "name": "Environmental"
        },
        {
            "name": "monitoring"
        },
        {
            "name": "facilities"
        },
        {
            "name": "Air"
        },
        {
            "name": "Athmospheric composition"
        },
        {
            "name": "GEMET"
        },
        
    ],
    "title": [
        "ICOS atmospheric near-realtime observational data"
    ],
    "url": "https://icos-cp.eu/"
}