{
    "DOI": "http://dx.doi.org/doi:10.15479/AT:ISTA:71",
    "DiscHierarchy": [],
    "Discipline": "Not stated",
    "Format": [
        "video"
    ],
    "MetaDataAccess": "http://datarep.app.ist.ac.at/cgi/oai2?verb=GetRecord&metadataPrefix=oai_dc&identifier=oai:datarep.app.ist.ac.at:71",
    "RelatedIdentifier": [
        "https://datarep.app.ist.ac.at/71/"
    ],
    "ResourceType": [
        "Data Collection"
    ],
    "author": [
        "Leithner, Alexander"
    ],
    "fulltext": "oai:datarep.app.ist.ac.at:71;2017-08-09T11:38:28Z;Immunological synapse DC-Tcells;Leithner, Alexander;570 Life sciences; biology;Immunological synapse DC-Tcells;Data Collection;NonPeerReviewed;video;video;https://datarep.app.ist.ac.at/71/;https://datarep.app.ist.ac.at/71/1/Synapse_1.avi;https://datarep.app.ist.ac.at/71/2/Synapse_2.avi;  Leithner, Alexander   Immunological synapse DC-Tcells.  [Data Collection]    (Unpublished)  ;10.15479/AT:ISTA:71;10.15479/AT:ISTA:71",
    "group": "ist",
    "groups": [
        {
            "name": "ist"
        }
    ],
    "name": "6a68830e-28eb-5c2d-a869-8f901ccc7b81",
    "notes": [
        "Immunological synapse DC-Tcells"
    ],
    "oai_identifier": [
        "oai:datarep.app.ist.ac.at:71"
    ],
    "oai_set": "",
    "state": "active",
    "tags": [
        {
            "name": "Life sciences"
        },
        {
            "name": "biology"
        }
    ],
    "title": [
        "Immunological synapse DC-Tcells"
    ],
    "url": "https://datarep.app.ist.ac.at/71/2/Synapse_2.avi"
}