{
    "Contact": [
        "atm-data@helsinki.fi"
    ],
    "DiscHierarchy": [],
    "Discipline": "Not stated",
    "MetaDataAccess": "https://etsin.avointiede.fi/oai?verb=GetRecord&metadataPrefix=oai_dc&identifier=0af81d46-7341-5c9e-a56e-d9df530e3a1c",
    "PublicationTimestamp": "2016-03-08T11:59:59Z",
    "PublicationYear": [
        "2016"
    ],
    "Publisher": [
        "atm-data@helsinki.fi"
    ],
    "ResourceType": [
        "dataset"
    ],
    "Rights": [
        "Creative Commons Attribution 4.0"
    ],
    "SpatialCoverage": [
        "DCMI-point: name=Hyyti\u00e4l\u00e4; east=24.294795; north=61.847463 elevation=179",
        "2000-01-01T00:00:00Z/2000-12-31T23:59:59Z"
    ],
    "TempCoverageBegin": 92982427199,
    "TempCoverageEnd": 63082281600,
    "TemporalCoverage": " period : ( 2947-07-01T11:59:59Z - 2000-01-01T00:00:00Z ) ",
    "TemporalCoverage:BeginDate": "2947-07-01T11:59:59Z",
    "TemporalCoverage:EndDate": "2000-01-01T00:00:00Z",
    "author": [
        "Pasi Aalto"
    ],
    "fulltext": "urn:nbn:fi:csc-kata20160308110340318738;2016-03-08T09:03:40Z;university-of-helsinki-department-of-physics-division-of-atmospheric-sciences;Hyyti\u00e4l\u00e4 SMEAR II meteorology, gases and soil - Soil water content B1 - 2000;Pasi Aalto;http://www.yso.fi/onto/yso/p899;Title: Soil water content B1 \n\nDescription: Volumetric soil water content in B1 horizon (14-25 cm depth in the mineral soil), mean of five locations \n\nVariable: wsoil_B1 \n\nUnit: m\u00b3 m\u207b\u00b3 \n\nSource: Campbell TDR100 Time-Domain Reflectometer \n\nCategory: Soil \n\n;atm-data@helsinki.fi;2016-03-08;dataset;urn:nbn:fi:csc-ida-10x201703272015017309341v;urn:nbn:fi:csc-ida2014010803466v;urn:nbn:fi:csc-ida2014010803466s;urn:nbn:fi:csc-kata20160308110340318738;http://etsin.avointiede.fi/dataset/urn-nbn-fi-csc-kata20160308110340318738;DCMI-point: name=Hyyti\u00e4l\u00e4; east=24.294795; north=61.847463 elevation=179;2000-01-01T00:00:00Z/2000-12-31T23:59:59Z;Creative Commons Attribution 4.0",
    "group": "etsin",
    "groups": [
        {
            "name": "etsin"
        }
    ],
    "name": "0af81d46-7341-5c9e-a56e-d9df530e3a1c",
    "notes": [
        "Title: Soil water content B1 \n\nDescription: Volumetric soil water content in B1 horizon (14-25 cm depth in the mineral soil), mean of five locations \n\nVariable: wsoil_B1 \n\nUnit: m\u00b3 m\u207b\u00b3 \n\nSource: Campbell TDR100 Time-Domain Reflectometer \n\nCategory: Soil \n\n"
    ],
    "oai_identifier": [
        "0af81d46-7341-5c9e-a56e-d9df530e3a1c"
    ],
    "oai_set": "",
    "state": "active",
    "tags": [
        {
            "name": "http www.yso.fi onto yso p"
        }
    ],
    "title": [
        "Hyyti\u00e4l\u00e4 SMEAR II meteorology, gases and soil - Soil water content B1 - 2000"
    ],
    "url": "http://etsin.avointiede.fi/dataset/urn-nbn-fi-csc-kata20160308110340318738"
}