{
    "Contact": [
        "Universal Dependencies Consortium"
    ],
    "DiscHierarchy": [
        "1.4",
        "Humanities",
        "Linguistics"
    ],
    "Discipline": "Linguistics",
    "Format": [
        "text/plain; charset=utf-8",
        "application/x-gzip",
        "downloadable_files_count: 1"
    ],
    "Language": [
        "Ancient Greek (to 1453)",
        "Arabic",
        "Basque",
        "Bulgarian",
        "Croatian",
        "Czech",
        "Danish",
        "Dutch",
        "English",
        "Estonian",
        "Finnish",
        "French",
        "German",
        "Gothic",
        "Modern Greek (1453-)",
        "Hebrew",
        "Hindi",
        "Hungarian",
        "Indonesian",
        "Irish",
        "Italian",
        "Japanese",
        "Latin",
        "Norwegian",
        "Church Slavic",
        "Persian",
        "Polish",
        "Portuguese",
        "Romanian",
        "Slovenian",
        "Spanish",
        "Swedish",
        "Tamil",
        "Catalan",
        "Chinese",
        "Galician",
        "Kazakh",
        "Latvian",
        "Russian",
        "Turkish",
        "Coptic",
        "Sanskrit",
        "Slovak",
        "Ukrainian",
        "Uighur",
        "Vietnamese",
        "Belarusian",
        "Korean",
        "Lithuanian",
        "Urdu",
        "Northern Sami",
        "Upper Sorbian"
    ],
    "MetaDataAccess": "https://clarin-pl.eu/oai/request?verb=GetRecord&metadataPrefix=oai_dc&identifier=oai:lindat.mff.cuni.cz:11234/1-2184",
    "MetadataAccess": [
        "oai:lindat.mff.cuni.cz:11234/1-2184"
    ],
    "PID": "http://hdl.handle.net/11234/1-2184",
    "PublicationTimestamp": "2017-05-18T11:59:59Z",
    "PublicationYear": [
        "2017"
    ],
    "Publisher": [
        "Universal Dependencies Consortium"
    ],
    "ResourceType": [
        "corpus"
    ],
    "Rights": [
        "Licence Universal Dependencies v2.0",
        "https://lindat.mff.cuni.cz/repository/xmlui/page/licence-UD-2.0",
        "PUB"
    ],
    "author": [
        "Ion, Radu",
        "Seraji, Mojgan",
        "Manning, Christopher",
        "Cebiro\u011flu Eryi\u011fit, G\u00fcl\u015fen",
        "Ma\u0161ek, Jan",
        "Uszkoreit, Hans",
        "Hlav\u00e1\u010dov\u00e1, Jaroslava",
        "Passarotti, Marco",
        "Nguy\u1ec5n Th\u1ecb, L\u01b0\u01a1ng",
        "Zhu, Hanzhi",
        "Osenova, Petya",
        "Macketanz, Vivien",
        "Agi\u0107, \u017deljko",
        "Simionescu, Radu",
        "Muischnek, Kadri",
        "Choi, Jinho",
        "Montemagni, Simonetta",
        "Ojala, Stina",
        "Ure\u0161ov\u00e1, Zde\u0148ka",
        "Moskalevskyi, Bohdan",
        "Stella, Antonio",
        "Rovati, Davide",
        "Bank, Sebastian",
        "Seeker, Wolfgang",
        "Harris, Kim",
        "\u017dabokrtsk\u00fd, Zden\u011bk",
        "Sanguinetti, Manuela",
        "Cinkov\u00e1, Silvie",
        "Irimia, Elena",
        "Goldberg, Yoav",
        "Yu, Zhuoran",
        "Simk\u00f3, Katalin",
        "Simi, Maria",
        "Badmaeva, Elena",
        "Hladk\u00e1, Barbora",
        "Trosterud, Trond",
        "Krek, Simon",
        "G\u00f6k\u0131rmak, Memduh",
        "L\u00ea H\u1ed3ng, Ph\u01b0\u01a1ng",
        "\u00d8vrelid, Lilja",
        "Galbraith, Daniel",
        "Lenci, Alessandro",
        "Seddah, Djam\u00e9",
        "Martins, Andr\u00e9",
        "Ginter, Filip",
        "Mititelu, Verginica",
        "Erjavec, Toma\u017e",
        "Johannsen, Anders",
        "Bick, Eckhard",
        "Mart\u00ednez Alonso, H\u00e9ctor",
        "Kettnerov\u00e1, V\u00e1clava",
        "Kayadelen, Tolga",
        "Li, Josie",
        "Haug, Dag",
        "Rehm, Georg",
        "Lynn, Teresa",
        "Plank, Barbara",
        "Freitas, Cl\u00e1udia",
        "Varga, Viktor",
        "Lyashevskaya, Olga",
        "J\u00f8rgensen, Fredrik",
        "M\u0103r\u0103nduc, C\u0103t\u0103lina",
        "Ka\u015f\u0131kara, H\u00fcner",
        "Pyysalo, Sampo",
        "Kanerva, Jenna",
        "Sulubacak, Umut",
        "Sz\u00e1nt\u00f3, Zsolt",
        "Chalub, Fabricio",
        "Marheinecke, Katrin",
        "Atutxa, Aitziber",
        "Bauer, John",
        "Matsumoto, Yuji",
        "Dozat, Timothy",
        "Ateyah, Luma",
        "G\u00f3mez Guinovart, Xavier",
        "M\u00fc\u00fcrisep, Kaili",
        "Saul\u012bte, Baiba",
        "Caron, Gauthier",
        "Mandl, Michael",
        "Nivre, Joakim",
        "Prokopidis, Prokopis",
        "Petrov, Slav",
        "Reddy, Siva",
        "Guillaume, Bruno",
        "Gr\u016bz\u012btis, Normunds",
        "Cetin, Savas",
        "Haji\u010d jr., Jan",
        "Perrier, Guy",
        "Trukhina, Anna",
        "Nainwani, Pinkey",
        "de Marneffe, Marie-Catherine",
        "Antonsen, Lene",
        "Attia, Mohammed",
        "Schuster, Sebastian",
        "Missil\u00e4, Anna",
        "Perez, Cenel-Augusto",
        "Hohle, Petter",
        "Makazhanov, Aibek",
        "Tyers, Francis",
        "McDonald, Ryan",
        "Pretkalni\u0146a, Lauma",
        "Farkas, Rich\u00e1rd",
        "Moreno Romero, Laura",
        "Sawanakunanon, Yanin",
        "Washington, Jonathan North",
        "Bosco, Cristina",
        "Kirchner, Jesse",
        "Fernandez Alcalde, Hector",
        "Eli, Marhaba",
        "Mori, Shunsuke",
        "de Paiva, Valeria",
        "Grioni, Matias",
        "Real, Livy",
        "Lertpradit, Saran",
        "Asahara, Masayuki",
        "Pitler, Emily",
        "Suhr, Alane",
        "Tanaka, Takaaki",
        "Miyao, Yusuke",
        "Vincze, Veronika",
        "Kwak, Sookyoung",
        "Cho, Yongseok",
        "Bhat, Riyaz Ahmad",
        "Mustafina, Nina",
        "Garcia, Marcos",
        "Loginova, Olga",
        "Shimada, Atsuko",
        "Nguy\u1ec5n Th\u1ecb Minh, Huy\u1ec1n",
        "Nitisaroj, Rattima",
        "Puolakainen, Tiina",
        "Tsarfaty, Reut",
        "Taji, Dima",
        "Goenaga, Iakes",
        "Rituma, Laura",
        "H\u00e0 M\u1ef9, Linh",
        "Lambertino, Lorenzo",
        "Habash, Nizar",
        "Droganova, Kira",
        "Elkahky, Ali",
        "Connor, Miriam",
        "Mare\u010dek, David",
        "Smith, Aaron",
        "Banerjee, Esha",
        "Nedoluzhko, Anna",
        "Strnadov\u00e1, Jana",
        "More, Amir",
        "Mendon\u00e7a, Gustavo",
        "\u0160imkov\u00e1, M\u00e1ria",
        "Gajdo\u0161ov\u00e1, Katar\u00edna",
        "Zeman, Daniel",
        "Celano, Giuseppe G. A.",
        "Dobrovoljc, Kaja",
        "Popel, Martin",
        "Laippala, Veronika",
        "Gojenola, Koldo",
        "Lando, Tatiana",
        "Simov, Kiril",
        "Ballesteros, Miguel",
        "Nurmi, Hanna",
        "Nikolaev, Vitaly",
        "Rademaker, Alexandre",
        "Ljube\u0161i\u0107, Nikola",
        "Ahrenberg, Lars",
        "Shakurova, Lena",
        "Diaz de Ilarraza, Arantza",
        "Rosa, Rudolf",
        "Aranzabe, Maria Jesus",
        "Li, Cheuk Ying",
        "Candito, Marie",
        "Shen, Mo",
        "Saleh, Shadi",
        "Burchardt, Aljoscha",
        "Bengoetxea, Kepa",
        "Shohibussirri, Muh",
        "van Noord, Gertjan",
        "Pascual, Elena",
        "Rinaldi, Larissa",
        "Bouma, Gosse",
        "Foster, Jennifer",
        "\u00c7\u00f6ltekin, \u00c7a\u011fr\u0131",
        "Piitulainen, Jussi",
        "Uematsu, Sumire",
        "Gonz\u00e1les Saavedra, Berta",
        "Uria, Larraitz",
        "Manurung, Ruli",
        "Leung, Herman",
        "Kanayama, Hiroshi",
        "Haji\u010d, Jan",
        "Bowman, Sam",
        "Kotsyba, Natalia",
        "Silveira, Natalia"
    ],
    "fulltext": "oai:lindat.mff.cuni.cz:11234/1-2184;2018-07-02T22:05:50Z;hdl_11858_00-097C-0000-0001-486F-D;hdl_11858_00-097C-0000-0001-4877-A;Universal Dependencies 2.0 \u2013 CoNLL 2017 Shared Task Development and Test Data;Nivre, Joakim;Agi\u0107, \u017deljko;Ahrenberg, Lars;Antonsen, Lene;Aranzabe, Maria Jesus;Asahara, Masayuki;Ateyah, Luma;Attia, Mohammed;Atutxa, Aitziber;Badmaeva, Elena;Ballesteros, Miguel;Banerjee, Esha;Bank, Sebastian;Bauer, John;Bengoetxea, Kepa;Bhat, Riyaz Ahmad;Bick, Eckhard;Bosco, Cristina;Bouma, Gosse;Bowman, Sam;Burchardt, Aljoscha;Candito, Marie;Caron, Gauthier;Cebiro\u011flu Eryi\u011fit, G\u00fcl\u015fen;Celano, Giuseppe G. A.;Cetin, Savas;Chalub, Fabricio;Choi, Jinho;Cho, Yongseok;Cinkov\u00e1, Silvie;\u00c7\u00f6ltekin, \u00c7a\u011fr\u0131;Connor, Miriam;de Marneffe, Marie-Catherine;de Paiva, Valeria;Diaz de Ilarraza, Arantza;Dobrovoljc, Kaja;Dozat, Timothy;Droganova, Kira;Eli, Marhaba;Elkahky, Ali;Erjavec, Toma\u017e;Farkas, Rich\u00e1rd;Fernandez Alcalde, Hector;Foster, Jennifer;Freitas, Cl\u00e1udia;Gajdo\u0161ov\u00e1, Katar\u00edna;Galbraith, Daniel;Garcia, Marcos;Ginter, Filip;Goenaga, Iakes;Gojenola, Koldo;G\u00f6k\u0131rmak, Memduh;Goldberg, Yoav;G\u00f3mez Guinovart, Xavier;Gonz\u00e1les Saavedra, Berta;Grioni, Matias;Gr\u016bz\u012btis, Normunds;Guillaume, Bruno;Habash, Nizar;Haji\u010d, Jan;Haji\u010d jr., Jan;H\u00e0 M\u1ef9, Linh;Harris, Kim;Haug, Dag;Hladk\u00e1, Barbora;Hlav\u00e1\u010dov\u00e1, Jaroslava;Hohle, Petter;Ion, Radu;Irimia, Elena;Johannsen, Anders;J\u00f8rgensen, Fredrik;Ka\u015f\u0131kara, H\u00fcner;Kanayama, Hiroshi;Kanerva, Jenna;Kayadelen, Tolga;Kettnerov\u00e1, V\u00e1clava;Kirchner, Jesse;Kotsyba, Natalia;Krek, Simon;Kwak, Sookyoung;Laippala, Veronika;Lambertino, Lorenzo;Lando, Tatiana;L\u00ea H\u1ed3ng, Ph\u01b0\u01a1ng;Lenci, Alessandro;Lertpradit, Saran;Leung, Herman;Li, Cheuk Ying;Li, Josie;Ljube\u0161i\u0107, Nikola;Loginova, Olga;Lyashevskaya, Olga;Lynn, Teresa;Macketanz, Vivien;Makazhanov, Aibek;Mandl, Michael;Manning, Christopher;Manurung, Ruli;M\u0103r\u0103nduc, C\u0103t\u0103lina;Mare\u010dek, David;Marheinecke, Katrin;Mart\u00ednez Alonso, H\u00e9ctor;Martins, Andr\u00e9;Ma\u0161ek, Jan;Matsumoto, Yuji;McDonald, Ryan;Mendon\u00e7a, Gustavo;Missil\u00e4, Anna;Mititelu, Verginica;Miyao, Yusuke;Montemagni, Simonetta;More, Amir;Moreno Romero, Laura;Mori, Shunsuke;Moskalevskyi, Bohdan;Muischnek, Kadri;Mustafina, Nina;M\u00fc\u00fcrisep, Kaili;Nainwani, Pinkey;Nedoluzhko, Anna;Nguy\u1ec5n Th\u1ecb, L\u01b0\u01a1ng;Nguy\u1ec5n Th\u1ecb Minh, Huy\u1ec1n;Nikolaev, Vitaly;Nitisaroj, Rattima;Nurmi, Hanna;Ojala, Stina;Osenova, Petya;\u00d8vrelid, Lilja;Pascual, Elena;Passarotti, Marco;Perez, Cenel-Augusto;Perrier, Guy;Petrov, Slav;Piitulainen, Jussi;Pitler, Emily;Plank, Barbara;Popel, Martin;Pretkalni\u0146a, Lauma;Prokopidis, Prokopis;Puolakainen, Tiina;Pyysalo, Sampo;Rademaker, Alexandre;Real, Livy;Reddy, Siva;Rehm, Georg;Rinaldi, Larissa;Rituma, Laura;Rosa, Rudolf;Rovati, Davide;Saleh, Shadi;Sanguinetti, Manuela;Saul\u012bte, Baiba;Sawanakunanon, Yanin;Schuster, Sebastian;Seddah, Djam\u00e9;Seeker, Wolfgang;Seraji, Mojgan;Shakurova, Lena;Shen, Mo;Shimada, Atsuko;Shohibussirri, Muh;Silveira, Natalia;Simi, Maria;Simionescu, Radu;Simk\u00f3, Katalin;\u0160imkov\u00e1, M\u00e1ria;Simov, Kiril;Smith, Aaron;Stella, Antonio;Strnadov\u00e1, Jana;Suhr, Alane;Sulubacak, Umut;Sz\u00e1nt\u00f3, Zsolt;Taji, Dima;Tanaka, Takaaki;Trosterud, Trond;Trukhina, Anna;Tsarfaty, Reut;Tyers, Francis;Uematsu, Sumire;Ure\u0161ov\u00e1, Zde\u0148ka;Uria, Larraitz;Uszkoreit, Hans;van Noord, Gertjan;Varga, Viktor;Vincze, Veronika;Washington, Jonathan North;Yu, Zhuoran;\u017dabokrtsk\u00fd, Zden\u011bk;Zeman, Daniel;Zhu, Hanzhi;treebank;dependency;syntax;morphology;harmonized annotation;interset;universal tagset;stanford dependencies;Universal Dependencies is a project that seeks to develop cross-linguistically consistent treebank annotation for many languages, with the goal of facilitating multilingual parser development, cross-lingual learning, and parsing research from a language typology perspective. The annotation scheme is based on (universal) Stanford dependencies (de Marneffe et al., 2006, 2008, 2014), Google universal part-of-speech tags (Petrov et al., 2012), and the Interset interlingua for morphosyntactic tagsets (Zeman, 2008).\r\n\r\nThis release contains the test data used in the CoNLL 2017 shared task on parsing Universal Dependencies. Due to the shared task the test data was held hidden and not released together with the training and development data of UD 2.0. Therefore this release complements the UD 2.0 release (http://hdl.handle.net/11234/1-1983) to a full release of UD treebanks. In addition, the present release contains 18 new parallel test sets and 4 test sets in surprise languages. The present release also includes the development data already released with UD 2.0. Unlike regular UD releases, this one uses the folder-file structure that was visible to the systems participating in the shared task.;2017-05-18;corpus;http://hdl.handle.net/11234/1-2184;grc;ara;eus;bul;hrv;ces;dan;nld;eng;est;fin;fra;deu;got;ell;heb;hin;hun;ind;gle;ita;jpn;lat;nor;chu;fas;pol;por;ron;slv;spa;swe;tam;cat;zho;glg;kaz;lav;rus;tur;cop;san;slk;ukr;uig;vie;bel;kor;lit;urd;sme;hsb;bxr;kmr;Licence Universal Dependencies v2.0;https://lindat.mff.cuni.cz/repository/xmlui/page/licence-UD-2.0;PUB;application/x-gzip;text/plain; charset=utf-8;downloadable_files_count: 1;Universal Dependencies Consortium;http://universaldependencies.org/conll17/",
    "group": "clarin",
    "groups": [
        {
            "name": "clarin"
        }
    ],
    "name": "0a8928a1-b026-5c83-8cc3-430e0b560c63",
    "notes": [
        "Universal Dependencies is a project that seeks to develop cross-linguistically consistent treebank annotation for many languages, with the goal of facilitating multilingual parser development, cross-lingual learning, and parsing research from a language typology perspective. The annotation scheme is based on (universal) Stanford dependencies (de Marneffe et al., 2006, 2008, 2014), Google universal part-of-speech tags (Petrov et al., 2012), and the Interset interlingua for morphosyntactic tagsets (Zeman, 2008).\r\n\r\nThis release contains the test data used in the CoNLL 2017 shared task on parsing Universal Dependencies. Due to the shared task the test data was held hidden and not released together with the training and development data of UD 2.0. Therefore this release complements the UD 2.0 release (http://hdl.handle.net/11234/1-1983) to a full release of UD treebanks. In addition, the present release contains 18 new parallel test sets and 4 test sets in surprise languages. The present release also includes the development data already released with UD 2.0. Unlike regular UD releases, this one uses the folder-file structure that was visible to the systems participating in the shared task."
    ],
    "oai_identifier": [
        "oai:lindat.mff.cuni.cz:11234/1-2184"
    ],
    "oai_set": [
        "hdl_11858_00-097C-0000-0001-486F-D",
        "hdl_11858_00-097C-0000-0001-4877-A"
    ],
    "state": "active",
    "tags": [
        {
            "name": "treebank"
        },
        {
            "name": "dependency"
        },
        {
            "name": "syntax"
        },
        {
            "name": "morphology"
        },
        {
            "name": "harmonized annotation"
        },
        {
            "name": "interset"
        },
        {
            "name": "universal tagset"
        },
        {
            "name": "stanford dependencies"
        }
    ],
    "title": [
        "Universal Dependencies 2.0 \u2013 CoNLL 2017 Shared Task Development and Test Data"
    ],
    "url": ""
}