{
    "Contact": [
        "TALG Research Group (University of Vigo)"
    ],
    "DiscHierarchy": [
        "1.4",
        "Humanities",
        "Linguistics"
    ],
    "Discipline": "Linguistics",
    "Format": [
        "downloadable_files_count: 0"
    ],
    "Language": [
        "Galician"
    ],
    "MetaDataAccess": "https://clarin-pl.eu/oai/request?verb=GetRecord&metadataPrefix=oai_dc&identifier=oai:lindat.mff.cuni.cz:11372/LRT-617",
    "MetadataAccess": [
        "oai:lindat.mff.cuni.cz:11372/LRT-617"
    ],
    "PID": "http://hdl.handle.net/11372/LRT-617",
    "PublicationTimestamp": "2014-07-30T11:59:59Z",
    "PublicationYear": [
        "2014"
    ],
    "Publisher": [
        "TALG Research Group (University of Vigo)"
    ],
    "ResourceType": [
        "lexicalConceptualResource"
    ],
    "SpatialCoverage": [
        "Spain"
    ],
    "TemporalCoverage": " point in time : None",
    "fulltext": "oai:lindat.mff.cuni.cz:11372/LRT-617;2016-04-06T16:39:52Z;hdl_11858_00-097C-0000-0007-710A-A;hdl_11858_00-097C-0000-0007-710B-8;Neoteca;Galician neology databank;2014-07-30;lexicalConceptualResource;http://hdl.handle.net/11372/LRT-617;glg;downloadable_files_count: 0;Spain;TALG Research Group (University of Vigo);http://sli.uvigo.es/neoteca",
    "group": "clarin",
    "groups": [
        {
            "name": "clarin"
        }
    ],
    "name": "1f847ece-3ea5-5c19-859d-46277d446158",
    "notes": [
        "Galician neology databank"
    ],
    "oai_identifier": [
        "oai:lindat.mff.cuni.cz:11372/LRT-617"
    ],
    "oai_set": [
        "hdl_11858_00-097C-0000-0007-710A-A",
        "hdl_11858_00-097C-0000-0007-710B-8"
    ],
    "state": "active",
    "title": [
        "Neoteca"
    ],
    "url": ""
}