{
    "Contact": [
        "Institute of Computer Science, Polish Academy of Sciences"
    ],
    "DiscHierarchy": [
        "1.4",
        "Humanities",
        "Linguistics"
    ],
    "Discipline": "Linguistics",
    "Format": [
        "downloadable_files_count: 0"
    ],
    "Language": [
        "Polish"
    ],
    "MetaDataAccess": "https://clarin-pl.eu/oai/request?verb=GetRecord&metadataPrefix=oai_dc&identifier=oai:clarin-pl.eu:11321/467",
    "MetadataAccess": [
        "oai:clarin-pl.eu:11321/467"
    ],
    "PID": "http://hdl.handle.net/11321/467",
    "PublicationTimestamp": "2018-07-01T11:59:59Z",
    "PublicationYear": [
        "2018"
    ],
    "Publisher": [
        "Institute of Computer Science, Polish Academy of Sciences"
    ],
    "ResourceType": [
        "corpus"
    ],
    "author": [
        "Ogrodniczuk, Maciej"
    ],
    "fulltext": "oai:clarin-pl.eu:11321/467;2018-05-07T01:38:44Z;hdl_11321_3;hdl_11321_4;Polish Parliamentary Corpus;Ogrodniczuk, Maciej;Polish;parliamentary data;corpus;The Polish Parliamentary Corpus (PPC) is a large collection of linguistically analysed documents from the proceedings of Polish Parliament, Sejm and Senate. The corpus files are made available in TEI P5 format compatible with the annotation used by the National Corpus of Polish.;2018;corpus;http://hdl.handle.net/11321/467;pol;downloadable_files_count: 0;Institute of Computer Science, Polish Academy of Sciences;http://clip.ipipan.waw.pl/PPC",
    "group": "clarin",
    "groups": [
        {
            "name": "clarin"
        }
    ],
    "name": "26dfe28b-da32-5cd0-81d8-46252f7b9aec",
    "notes": [
        "The Polish Parliamentary Corpus (PPC) is a large collection of linguistically analysed documents from the proceedings of Polish Parliament, Sejm and Senate. The corpus files are made available in TEI P5 format compatible with the annotation used by the National Corpus of Polish."
    ],
    "oai_identifier": [
        "oai:clarin-pl.eu:11321/467"
    ],
    "oai_set": [
        "hdl_11321_3",
        "hdl_11321_4"
    ],
    "state": "active",
    "tags": [
        {
            "name": "Polish"
        },
        {
            "name": "parliamentary data"
        },
        {
            "name": "corpus"
        }
    ],
    "title": [
        "Polish Parliamentary Corpus"
    ],
    "url": ""
}