{
    "Contact": [
        "Oxford Text Archive, University of Oxford"
    ],
    "DiscHierarchy": [
        "1.4",
        "Humanities",
        "Linguistics"
    ],
    "Discipline": "Linguistics",
    "Format": [
        "text/sgml",
        "(1 file : ca. 79.3 KB)"
    ],
    "Language": [
        "English"
    ],
    "MetaDataAccess": "https://clarin-pl.eu/oai/request?verb=GetRecord&metadataPrefix=oai_dc&identifier=oai:ota:oucs:1565",
    "MetadataAccess": [
        "oai:ota:oucs:1565"
    ],
    "PublicationTimestamp": "1976-01-01T11:59:59Z",
    "PublicationYear": [
        "1976"
    ],
    "Publisher": [
        "Oxford Text Archive, University of Oxford"
    ],
    "ResourceType": [
        "Text"
    ],
    "Rights": [
        "Distributed by the University of Oxford under a Creative Commons Attribution-NonCommercial-ShareAlike 3.0 Unported License.",
        "http://www.ota.ox.ac.uk/documents/user_agreement.xml"
    ],
    "author": [
        "Fielding, Henry, 1707-1754"
    ],
    "fulltext": "oai:ota:oucs:1565;2018-07-02T14:44:52Z;http://ota.ox.ac.uk/headers/1565.xml;Shamela;Fielding, Henry, 1707-1754;default: 1976-01-01;text_and_corpus_linguistics;Fiction -- Great Britain -- 18th century;Novels -- Great Britain -- 18th century;Parodies -- Great Britain -- 18th century;eng;Oxford Text Archive, University of Oxford;text/sgml;(1 file : ca. 79.3 KB);Text;Distributed by the University of Oxford under a Creative Commons Attribution-NonCommercial-ShareAlike 3.0 Unported License.;http://www.ota.ox.ac.uk/documents/user_agreement.xml",
    "group": "clarin",
    "groups": [
        {
            "name": "clarin"
        }
    ],
    "name": "2b961a00-2b72-5e43-846a-8d2027c76a5b",
    "oai_identifier": [
        "oai:ota:oucs:1565"
    ],
    "oai_set": "",
    "state": "active",
    "tags": [
        {
            "name": "text_and_corpus_linguistics"
        },
        {
            "name": "Fiction -- Great Britain -- th century"
        },
        {
            "name": "Novels -- Great Britain -- th century"
        },
        {
            "name": "Parodies -- Great Britain -- th century"
        }
    ],
    "title": [
        "Shamela"
    ],
    "url": "http://ota.ox.ac.uk/headers/1565.xml"
}