{
    "Contact": [
        "University of Warsaw"
    ],
    "DiscHierarchy": [
        "1.4",
        "Humanities",
        "Linguistics"
    ],
    "Discipline": "Linguistics",
    "Format": [
        "text/plain; charset=utf-8",
        "application/vnd.openxmlformats-officedocument.wordprocessingml.document",
        "application/vnd.oasis.opendocument.text",
        "downloadable_files_count: 10",
        "text/plain",
        "application/msword"
    ],
    "Language": [
        "Polish"
    ],
    "MetaDataAccess": "https://clarin-pl.eu/oai/request?verb=GetRecord&metadataPrefix=oai_dc&identifier=oai:clarin-pl.eu:11321/371",
    "MetadataAccess": [
        "oai:clarin-pl.eu:11321/371"
    ],
    "PID": "http://hdl.handle.net/11321/371",
    "PublicationTimestamp": "2017-05-30T11:59:59Z",
    "PublicationYear": [
        "2017"
    ],
    "Publisher": [
        "University of Warsaw"
    ],
    "ResourceType": [
        "corpus"
    ],
    "Rights": [
        "Creative Commons - Attribution-ShareAlike 4.0 International (CC BY-SA 4.0)",
        "http://creativecommons.org/licenses/by-sa/4.0/",
        "CC"
    ],
    "author": [
        "Peljak-\u0141api\u0144ska, Angelika"
    ],
    "fulltext": "oai:clarin-pl.eu:11321/371;2017-05-30T07:54:23Z;hdl_11321_3;hdl_11321_4;Test corpus;Peljak-\u0141api\u0144ska, Angelika;various;Test corpus of Polish texts;2017-05-30;corpus;http://hdl.handle.net/11321/371;pol;Creative Commons - Attribution-ShareAlike 4.0 International (CC BY-SA 4.0);http://creativecommons.org/licenses/by-sa/4.0/;CC;text/plain; charset=utf-8;application/vnd.oasis.opendocument.text;application/vnd.openxmlformats-officedocument.wordprocessingml.document;text/plain;application/vnd.openxmlformats-officedocument.wordprocessingml.document;application/msword;text/plain;application/vnd.openxmlformats-officedocument.wordprocessingml.document;application/msword;application/vnd.oasis.opendocument.text;text/plain;downloadable_files_count: 10;University of Warsaw",
    "group": "clarin",
    "groups": [
        {
            "name": "clarin"
        }
    ],
    "name": "404d7707-9932-577c-ba3a-95e631ec386a",
    "notes": [
        "Test corpus of Polish texts"
    ],
    "oai_identifier": [
        "oai:clarin-pl.eu:11321/371"
    ],
    "oai_set": [
        "hdl_11321_3",
        "hdl_11321_4"
    ],
    "state": "active",
    "tags": [
        {
            "name": "various"
        }
    ],
    "title": [
        "Test corpus"
    ],
    "url": ""
}