{
    "Contact": [
        "Research Institute for the Languages of Finland"
    ],
    "Contributor": [
        "Suutari, Toni"
    ],
    "DiscHierarchy": [
        "1.4",
        "Humanities",
        "Linguistics"
    ],
    "Discipline": "Linguistics",
    "Format": [
        "downloadable_files_count: 0"
    ],
    "MetaDataAccess": "https://clarin-pl.eu/oai/request?verb=GetRecord&metadataPrefix=oai_dc&identifier=oai:lindat.mff.cuni.cz:11372/LRT-834",
    "MetadataAccess": [
        "oai:lindat.mff.cuni.cz:11372/LRT-834"
    ],
    "PID": "http://hdl.handle.net/11372/LRT-834",
    "PublicationTimestamp": "2014-07-30T11:59:59Z",
    "PublicationYear": [
        "2014"
    ],
    "Publisher": [
        "Research Institute for the Languages of Finland"
    ],
    "ResourceType": [
        "lexicalConceptualResource"
    ],
    "fulltext": "oai:lindat.mff.cuni.cz:11372/LRT-834;2016-04-06T16:39:55Z;hdl_11858_00-097C-0000-0007-710A-A;hdl_11858_00-097C-0000-0007-710B-8;Electronic Vepsian Word List;Suutari, Toni;2014-07-30;lexicalConceptualResource;http://hdl.handle.net/11372/LRT-834;downloadable_files_count: 0;Research Institute for the Languages of Finland;http://kaino.kotus.fi/sanat/vepsa/",
    "group": "clarin",
    "groups": [
        {
            "name": "clarin"
        }
    ],
    "name": "5acad8de-e8f0-50f1-bef4-bde0b3f98f22",
    "oai_identifier": [
        "oai:lindat.mff.cuni.cz:11372/LRT-834"
    ],
    "oai_set": [
        "hdl_11858_00-097C-0000-0007-710A-A",
        "hdl_11858_00-097C-0000-0007-710B-8"
    ],
    "state": "active",
    "title": [
        "Electronic Vepsian Word List"
    ],
    "url": ""
}