{
    "Contact": [
        "Oxford Text Archive, University of Oxford"
    ],
    "DiscHierarchy": [
        "1.4",
        "Humanities",
        "Linguistics"
    ],
    "Discipline": "Linguistics",
    "Language": [
        "English"
    ],
    "MetaDataAccess": "https://clarin-pl.eu/oai/request?verb=GetRecord&metadataPrefix=oai_dc&identifier=oai:ota:oucs:3184",
    "MetadataAccess": [
        "oai:ota:oucs:3184"
    ],
    "PublicationTimestamp": "1550-07-01T11:59:59Z",
    "PublicationYear": [
        "1550"
    ],
    "Publisher": [
        "Oxford Text Archive, University of Oxford"
    ],
    "ResourceType": [
        "Text"
    ],
    "Rights": [
        "http://www.ota.ox.ac.uk/documents/user_agreement.xml"
    ],
    "author": [
        "Sherry, Richard, ca. 1506-ca. 1555"
    ],
    "fulltext": "oai:ota:oucs:3184;2018-07-02T14:44:52Z;http://ota.ox.ac.uk/headers/3184.xml;A treatise of schemes & tropes: very profytable for the better understanding of good authors, gathered out of the best grammarians & oratours ;Sherry, Richard, ca. 1506-ca. 1555;not after: 1550;text_and_corpus_linguistics;Textbooks -- England -- 16th century;eng;Oxford Text Archive, University of Oxford;Text;http://www.ota.ox.ac.uk/documents/user_agreement.xml",
    "group": "clarin",
    "groups": [
        {
            "name": "clarin"
        }
    ],
    "name": "68ba9c5a-f60d-5a1d-b299-2b1c492f09cc",
    "oai_identifier": [
        "oai:ota:oucs:3184"
    ],
    "oai_set": "",
    "state": "active",
    "tags": [
        {
            "name": "text_and_corpus_linguistics"
        },
        {
            "name": "Textbooks -- England -- th century"
        }
    ],
    "title": [
        "A treatise of schemes & tropes: very profytable for the better understanding of good authors, gathered out of the best grammarians & oratours "
    ],
    "url": "http://ota.ox.ac.uk/headers/3184.xml"
}