{
    "Contact": [
        "Institute of Mathematics and Computer Science, University of Latvia"
    ],
    "Contributor": [
        "Pinnis, M\u0101rcis",
        "Auzi\u0146a, Ilze",
        "Gr\u016bz\u012btis, Normunds",
        "Rostoks, Valters"
    ],
    "DiscHierarchy": [
        "1.4",
        "Humanities",
        "Linguistics"
    ],
    "Discipline": "Linguistics",
    "Format": [
        "downloadable_files_count: 0"
    ],
    "Language": [
        "Latvian"
    ],
    "MetaDataAccess": "https://clarin-pl.eu/oai/request?verb=GetRecord&metadataPrefix=oai_dc&identifier=oai:lindat.mff.cuni.cz:11372/LRT-1218",
    "MetadataAccess": [
        "oai:lindat.mff.cuni.cz:11372/LRT-1218"
    ],
    "PID": "http://hdl.handle.net/11372/LRT-1218",
    "PublicationTimestamp": "2014-07-30T11:59:59Z",
    "PublicationYear": [
        "2014"
    ],
    "Publisher": [
        "Institute of Mathematics and Computer Science, University of Latvia"
    ],
    "ResourceType": [
        "toolService"
    ],
    "SpatialCoverage": [
        "Latvia"
    ],
    "TemporalCoverage": " point in time : None",
    "fulltext": "oai:lindat.mff.cuni.cz:11372/LRT-1218;2016-04-06T16:39:50Z;hdl_11858_00-097C-0000-0007-710A-A;hdl_11858_00-097C-0000-0007-710B-8;Latvian Text-to-Speech Synthesizer;Pinnis, M\u0101rcis;Gr\u016bz\u012btis, Normunds;Rostoks, Valters;Auzi\u0146a, Ilze;Latvian Text-to-Speech Synthesizer: a RESTful web service.;2014-07-30;toolService;http://hdl.handle.net/11372/LRT-1218;lav;downloadable_files_count: 0;Latvia;Institute of Mathematics and Computer Science, University of Latvia;http://valoda.ailab.lv/ws/tts.jsp",
    "group": "clarin",
    "groups": [
        {
            "name": "clarin"
        }
    ],
    "name": "bc27fca6-82bc-5d0a-8ffa-9dade22eb0a4",
    "notes": [
        "Latvian Text-to-Speech Synthesizer: a RESTful web service."
    ],
    "oai_identifier": [
        "oai:lindat.mff.cuni.cz:11372/LRT-1218"
    ],
    "oai_set": [
        "hdl_11858_00-097C-0000-0007-710A-A",
        "hdl_11858_00-097C-0000-0007-710B-8"
    ],
    "state": "active",
    "title": [
        "Latvian Text-to-Speech Synthesizer"
    ],
    "url": ""
}