{
    "Contact": [
        "Oxford Text Archive, University of Oxford"
    ],
    "DiscHierarchy": [
        "1.4",
        "Humanities",
        "Linguistics"
    ],
    "Discipline": "Linguistics",
    "Language": [
        "English"
    ],
    "MetaDataAccess": "https://clarin-pl.eu/oai/request?verb=GetRecord&metadataPrefix=oai_dc&identifier=oai:ota:oucs:4715",
    "MetadataAccess": [
        "oai:ota:oucs:4715"
    ],
    "Publisher": [
        "Oxford Text Archive, University of Oxford"
    ],
    "ResourceType": [
        "Text"
    ],
    "Rights": [
        "http://www.ota.ox.ac.uk/documents/user_agreement.xml"
    ],
    "author": [
        "Coxe, William, 1747-1828."
    ],
    "fulltext": "oai:ota:oucs:4715;2017-06-15T11:47:03Z;http://ota.ox.ac.uk/headers/4715.xml;Sketches of the natural, civil, and political state of Swisserland: in a series of letters to William Melmoth, Esq; from William Coxe, ...;Coxe, William, 1747-1828.;text_and_corpus_linguistics;eng;Oxford Text Archive, University of Oxford;Text;http://www.ota.ox.ac.uk/documents/user_agreement.xml",
    "group": "clarin",
    "groups": [
        {
            "name": "clarin"
        }
    ],
    "name": "deca9dac-f465-5e65-9ebd-2b722bf2d60c",
    "oai_identifier": [
        "oai:ota:oucs:4715"
    ],
    "oai_set": "",
    "state": "active",
    "tags": [
        {
            "name": "text_and_corpus_linguistics"
        }
    ],
    "title": [
        "Sketches of the natural, civil, and political state of Swisserland: in a series of letters to William Melmoth, Esq; from William Coxe, ..."
    ],
    "url": "http://ota.ox.ac.uk/headers/4715.xml"
}