{
    "DiscHierarchy": [
        "4.4.6",
        "Geosciences",
        "Earth System Research"
    ],
    "Discipline": "Earth System Research",
    "Format": [
        "text/tab-separated-values"
    ],
    "Language": [
        "English"
    ],
    "MetadataAccess": [
        "oai:pangaea.de:doi:10.1594/PANGAEA.887859"
    ],
    "PublicationTimestamp": "2018-07-01T11:59:59Z",
    "PublicationYear": [
        "2018"
    ],
    "Publisher": [
        "PANGAEA - Data Publisher for Earth & Environmental Science"
    ],
    "ResourceType": [
        "Dataset"
    ],
    "Rights": [
        "Creative Commons Attribution 3.0 Unported (CC-BY)"
    ],
    "SpatialCoverage": "(83N-87N,13E-62E)",
    "TempCoverageBegin": 63609533999,
    "TempCoverageEnd": 63609533999,
    "TemporalCoverage": " point in time : 2016-09-15T11:59:59Z",
    "TemporalCoverage:BeginDate": "2016-09-15T11:59:59Z",
    "TemporalCoverage:EndDate": "2016-09-15T11:59:59Z",
    "author": [
        "Jacobs, Mirta",
        "N\u00f6thig, Eva-Maria",
        "Lorenzen, Christiane",
        "Strache, Anique"
    ],
    "fulltext": "oai:pangaea.de:doi:10.1594/PANGAEA.887859;2018-05-31T14:49:19Z;FRAM;https://doi.pangaea.de/10.1594/PANGAEA.887859;N\u00f6thig, Eva-Maria;0000-0002-7527-7827;Strache, Anique;Jacobs, Mirta;Lorenzen, Christiane;Chlorophyll a measured on water bottle samples during POLARSTERN cruise PS101 (ARK-XXX/3);PANGAEA - Data Publisher for Earth & Environmental Science;2018;Event label;Date/Time of event;Latitude of event;Longitude of event;Elevation of event;DEPTH, water;Chlorophyll a;PS101;Polarstern;Biological Oceanography @ AWI (AWI_BioOce);FRontiers in Arctic marine Monitoring (FRAM);Alfred Wegener Institute, Helmholtz Center for Polar and Marine Research, Bremerhaven;2016-09-15T10:07:00/2016-10-15T07:16:00;eng;Dataset;https://doi.pangaea.de/10.1594/PANGAEA.887882;10.2312/BzPM_0706_2017;10.1594/PANGAEA.871926;10.1594/PANGAEA.871927;60 data points;text/tab-separated-values;Creative Commons Attribution 3.0 Unported (CC-BY);82.88467 13.03183 87.10467 61.83767",
    "oai_identifier": [
        "oai:pangaea.de:doi:10.1594/PANGAEA.887859"
    ],
    "oai_set": [
        "FRAM"
    ],
    "spatial": "{\"type\":\"Polygon\",\"coordinates\":[[[13.03183,82.88467],[13.03183,87.10467],[61.83767,87.10467],[61.83767,82.88467],[13.03183,82.88467]]]}",
    "tags": [
        {
            "name": "PS"
        },
        {
            "name": "Polarstern"
        },
        {
            "name": "Biological Oceanography AWI AWI_BioOce"
        },
        {
            "name": "FRontiers Arctic marine Monitoring FRAM"
        }
    ],
    "title": [
        "Chlorophyll a measured on water bottle samples during POLARSTERN cruise PS101 (ARK-XXX/3)"
    ],
    "url": "https://doi.pangaea.de/10.1594/PANGAEA.887859"
}